examples/basic-async/main.py
examples/basic-sync/main.py
examples/django-integration/manage.py
examples/django-integration/config/__init__.py
examples/django-integration/config/settings.py
examples/django-integration/config/urls.py
examples/django-integration/config/wsgi.py
examples/django-integration/demo/__init__.py
examples/django-integration/demo/apps.py
examples/django-integration/demo/middleware.py
examples/django-integration/demo/replane_client.py
examples/django-integration/demo/urls.py
examples/django-integration/demo/views.py
examples/fastapi-integration/app.py
examples/feature-flags/main.py
examples/flask-integration/app.py
examples/testing/app.py
examples/testing/test_app.py
replane/__init__.py
replane/_async.py
replane/_eval.py
replane/_sse.py
replane/_sync.py
replane/errors.py
replane/py.typed
replane/testing.py
replane/types.py
replane/version.py
replane-0.6.0.dist-info/licenses/LICENSE
replane-0.6.0.dist-info/METADATA
replane-0.6.0.dist-info/WHEEL
replane-0.6.0.dist-info/top_level.txt
replane-0.6.0.dist-info/RECORD
