Metadata-Version: 2.4
Name: replane
Version: 0.6.0
Summary: Python SDK for Replane - dynamic configuration platform with real-time updates
Author-email: Dmitry Tilyupo <tilyupo@gmail.com>
License: MIT License
Project-URL: Homepage, https://github.com/replane-dev/replane-python
Project-URL: Repository, https://github.com/replane-dev/replane-python
Project-URL: Changelog, https://github.com/replane-dev/replane-python/blob/main/CHANGELOG.md
Classifier: Development Status :: 4 - Beta
Classifier: Intended Audience :: Developers
Classifier: License :: OSI Approved :: MIT License
Classifier: Programming Language :: Python :: 3
Classifier: Programming Language :: Python :: 3.10
Classifier: Programming Language :: Python :: 3.11
Classifier: Programming Language :: Python :: 3.12
Classifier: Programming Language :: Python :: 3.13
Classifier: Topic :: Software Development :: Libraries :: Python Modules
Classifier: Typing :: Typed
Requires-Python: >=3.10
License-File: LICENSE
Provides-Extra: async
Requires-Dist: httpx>=0.25.0; extra == "async"
Provides-Extra: dev
Requires-Dist: httpx>=0.25.0; extra == "dev"
Requires-Dist: ruff; extra == "dev"
Requires-Dist: mypy<2.0,>=1.0; extra == "dev"
Requires-Dist: pytest; extra == "dev"
Requires-Dist: pytest-asyncio; extra == "dev"
Requires-Dist: pytest-cov; extra == "dev"
Requires-Dist: twine>=1.11.0; extra == "dev"
Requires-Dist: build; extra == "dev"
Requires-Dist: setuptools; extra == "dev"
Requires-Dist: wheel; extra == "dev"
Requires-Dist: isort; extra == "dev"
Requires-Dist: black; extra == "dev"
Requires-Dist: sphinx; extra == "dev"
Requires-Dist: myst-parser; extra == "dev"
Requires-Dist: sphinx-copybutton; extra == "dev"
Requires-Dist: sphinx-autodoc-typehints; extra == "dev"
Requires-Dist: furo; extra == "dev"
Dynamic: license-file
